CHANGES.txt
LICENCE.txt
MANIFEST.in
README.md
setup.py
pysugarscape/GUI.py
pysugarscape/__init__.py
pysugarscape/model.py
pysugarscape.egg-info/PKG-INFO
pysugarscape.egg-info/SOURCES.txt
pysugarscape.egg-info/dependency_links.txt
pysugarscape.egg-info/entry_points.txt
pysugarscape.egg-info/requires.txt
pysugarscape.egg-info/top_level.txt